wallet_sdk/VERSION
wallet_sdk/__init__.py
wallet_sdk/setup.py
wallet_sdk_Noah_Huppert-1.1.0.dist-info/LICENSE
wallet_sdk_Noah_Huppert-1.1.0.dist-info/METADATA
wallet_sdk_Noah_Huppert-1.1.0.dist-info/WHEEL
wallet_sdk_Noah_Huppert-1.1.0.dist-info/top_level.txt
wallet_sdk_Noah_Huppert-1.1.0.dist-info/RECORD
