Metadata-Version: 2.1
Name: wallet-sdk-Noah-Huppert
Version: 1.1.0
Summary: Wallet service API SDK
Home-page: https://github.com/Noah-Huppert/wallet-service/tree/master/py-sdk
Author: Noah Huppert
Author-email: contact@noahh.io
License: UNKNOWN
Platform: UNKNOWN
Classifier: Programming Language :: Python :: 3
Classifier: License :: OSI Approved :: MIT License
Classifier: Operating System :: OS Independent
Requires-Python: >=3.6
Requires-Dist: pyjwt
Requires-Dist: requests
Requires-Dist: voluptuous
